fmrai/__init__.py
fmrai/agent/__init__.py
fmrai/agent/__main__.py
fmrai/agent/agents/__init__.py
fmrai/agent/agents/transformers.py
fmrai/agent/api.py
fmrai/agent/app.py
fmrai/agent/logic.py
fmrai/agent/models.py
fmrai/agent/state.py
fmrai/analysis/__init__.py
fmrai/analysis/attention.py
fmrai/analysis/common.py
fmrai/analysis/ffn_kv.py
fmrai/analysis/structure.py
fmrai/fmrai.py
fmrai/instrument.py
fmrai/logging.py
fmrai/pasten/__init__.py
fmrai/pasten/simple_model.py
fmrai/test/__init__.py
fmrai/test/test_tracker.py
fmrai/tracker.py
fmrai-0.1.4.dist-info/METADATA
fmrai-0.1.4.dist-info/WHEEL
fmrai-0.1.4.dist-info/RECORD
