Metadata-Version: 2.1
Name: fmrai
Version: 0.1.4
Summary: 
Author: Jacob Zhitomirsky
Author-email: bizarrecake@gmail.com
Requires-Python: >=3.9,<4.0
Classifier: Programming Language :: Python :: 3
Classifier: Programming Language :: Python :: 3.9
Classifier: Programming Language :: Python :: 3.10
Classifier: Programming Language :: Python :: 3.11
Requires-Dist: bitsandbytes (>=0.41.1,<0.42.0)
Requires-Dist: bottle (>=0.12.25,<0.13.0)
Requires-Dist: datasets (>=2.14.5,<3.0.0)
Requires-Dist: fastapi (>=0.103.1,<0.104.0)
Requires-Dist: pydantic (>=2.4.1,<3.0.0)
Requires-Dist: pydot (>=1.4.2,<2.0.0)
Requires-Dist: requests (>=2.31.0,<3.0.0)
Requires-Dist: scikit-learn (>=1.3.0,<2.0.0)
Requires-Dist: seaborn (>=0.13.0,<0.14.0)
Requires-Dist: tqdm (>=4.66.1,<5.0.0)
Requires-Dist: transformers (>=4.34.0,<5.0.0)
Requires-Dist: typer (>=0.9.0,<0.10.0)
